__init__
couchbed
