Metadata-Version: 2.1
Name: couchbed
Version: 0.2.0
Summary: Logging into CouchDB.
Author: chocolate-icecream
Keywords: CouchDB
Classifier: Programming Language :: Python :: 3
Classifier: Programming Language :: Python :: 3 :: Only
Classifier: License :: OSI Approved :: MIT License
Classifier: Development Status :: 4 - Beta
Classifier: Intended Audience :: Science/Research
Requires-Python: >=3.6
License-File: LICENSE.txt
